{
	"PackID": "Warehouse",
	"PackName": "Warehouse",
	"Levels": [
		{
			"ID": "Warehouse\\Level_06_1",
			"DisplayName": "6 - 1"
		},
		{
			"ID": "Warehouse\\Level_06_2",
			"DisplayName": "6 - 2"
		},
		{
			"ID": "Warehouse\\Level_06_3",
			"DisplayName": "6 - 3"
		},
		{
			"ID": "Warehouse\\Level_06_4",
			"DisplayName": "6 - 4"
		},
		{
			"ID": "Warehouse\\Level_06_5",
			"DisplayName": "6 - 5"
		},
		{
			"ID": "Warehouse\\Level_07_1",
			"DisplayName": "7 - 1"
		},
		{
			"ID": "Warehouse\\Level_07_2",
			"DisplayName": "7 - 2"
		},
		{
			"ID": "Warehouse\\Level_07_3",
			"DisplayName": "7 - 3"
		},
		{
			"ID": "Warehouse\\Level_07_4",
			"DisplayName": "7 - 4"
		},
		{
			"ID": "Warehouse\\Level_07_5",
			"DisplayName": "7 - 5"
		},
		{
			"ID": "Warehouse\\Level_08_1",
			"DisplayName": "8 - 1"
		},
		{
			"ID": "Warehouse\\Level_08_2",
			"DisplayName": "8 - 2"
		},
		{
			"ID": "Warehouse\\Level_08_3",
			"DisplayName": "8 - 3"
		},
		{
			"ID": "Warehouse\\Level_08_4",
			"DisplayName": "8 - 4"
		},
		{
			"ID": "Warehouse\\Level_08_5",
			"DisplayName": "8 - 5"
		},
		{
			"ID": "Warehouse\\Level_09_1",
			"DisplayName": "9 - 1"
		},
		{
			"ID": "Warehouse\\Level_09_2",
			"DisplayName": "9 - 2"
		},
		{
			"ID": "Warehouse\\Level_09_3",
			"DisplayName": "9 - 3"
		},
		{
			"ID": "Warehouse\\Level_09_4",
			"DisplayName": "9 - 4"
		},
		{
			"ID": "Warehouse\\Level_09_5",
			"DisplayName": "9 - 5"
		},
		{
			"ID": "Warehouse\\Level_10_1",
			"DisplayName": "10 - 1"
		},
		{
			"ID": "Warehouse\\Level_10_2",
			"DisplayName": "10 - 2"
		},
		{
			"ID": "Warehouse\\Level_10_3",
			"DisplayName": "10 - 3"
		},
		{
			"ID": "Warehouse\\Level_10_4",
			"DisplayName": "10 - 4"
		},
		{
			"ID": "Warehouse\\Level_10_5",
			"DisplayName": "10 - 5"
		}
	]
}